flask_googletrans/__init__.py
Flask_Googletrans-0.11.dist-info/LICENSE
Flask_Googletrans-0.11.dist-info/METADATA
Flask_Googletrans-0.11.dist-info/WHEEL
Flask_Googletrans-0.11.dist-info/top_level.txt
Flask_Googletrans-0.11.dist-info/RECORD
